{"ProjectWatches":"{\"Value\":[]}","OpenedDocuments":"[{\"DocumentPath\":\"sample.xaml\",\"FactoryId\":\"{ACB8E7BA-F093-44C1-9B50-33ECA51AAE16}\"}]","ProjectBreakpoints":"{\"CodeBreakpoints\":{},\"Value\":{}}","Compiler":"2","ProjectActivitiesViewState":"{\"Main.xaml\":[{\"ActivityIdRef\":\"If_1\",\"IsAdvancedOptionsExpanded\":false,\"Widgets\":{\"Else\":{\"ShowExpanded\":false},\"Then\":{\"ShowExpanded\":true}}},{\"ActivityIdRef\":\"GetPassword_1\",\"IsAdvancedOptionsExpanded\":false,\"Widgets\":{}},{\"ActivityIdRef\":\"GetPassword_2\",\"IsAdvancedOptionsExpanded\":false,\"Widgets\":{}}],\"sample.xaml\":[{\"ActivityIdRef\":\"If_1\",\"IsAdvancedOptionsExpanded\":false,\"Widgets\":{\"Else\":{\"ShowExpanded\":false},\"Then\":{\"ShowExpanded\":true}}},{\"ActivityIdRef\":\"GetPassword_1\",\"IsAdvancedOptionsExpanded\":false,\"Widgets\":{}},{\"ActivityIdRef\":\"If_2\",\"IsAdvancedOptionsExpanded\":false,\"Widgets\":{\"Else\":{\"ShowExpanded\":false},\"Then\":{\"ShowExpanded\":true}}},{\"ActivityIdRef\":\"GetPassword_3\",\"IsAdvancedOptionsExpanded\":false,\"Widgets\":{}}],\"EMI Due/Main.xaml\":[{\"ActivityIdRef\":\"If_1\",\"IsAdvancedOptionsExpanded\":false,\"Widgets\":{\"Else\":{\"ShowExpanded\":false},\"Then\":{\"ShowExpanded\":true}}},{\"ActivityIdRef\":\"GetPassword_1\",\"IsAdvancedOptionsExpanded\":false,\"Widgets\":{}},{\"ActivityIdRef\":\"GetPassword_2\",\"IsAdvancedOptionsExpanded\":false,\"Widgets\":{}}]}"}